{
  "contacts": [
    {
      "name": "shgsht",
      "number": "34564",
      "id": 1
    },
    {
      "name": "fasg",
      "number": "34653",
      "id": 4
    },
    {
      "name": "dfgxgd",
      "number": "4353",
      "id": 6
    },
    {
      "name": "begbf",
      "number": "45454",
      "id": 7
    },
    {
      "name": "gfrgfw",
      "number": "4546",
      "id": 8
    },
    {
      "name": "fdbnghf",
      "number": "554466",
      "id": 9
    },
    {
      "name": "dfsgh",
      "number": "4645",
      "id": 10
    },
    {
      "name": "xgfhxf",
      "number": "57457",
      "id": 11
    },
    {
      "name": "ag",
      "number": "345",
      "id": 12
    }
  ]
}